invideo_ai_mcp/__init__.py
invideo_ai_mcp/api_client.py
invideo_ai_mcp/server.py
invideo_ai_mcp-0.0.5.dist-info/METADATA
invideo_ai_mcp-0.0.5.dist-info/WHEEL
invideo_ai_mcp-0.0.5.dist-info/entry_points.txt
invideo_ai_mcp-0.0.5.dist-info/top_level.txt
invideo_ai_mcp-0.0.5.dist-info/RECORD
