Metadata-Version: 2.4
Name: invideo-ai-mcp
Version: 0.0.5
Summary: The invideo-ai MCP server enables any MCP Client like Claude Desktop or Agents to use the invideo-ai API to generate videos.
Author-email: Invideo Developers <dev@invideo.io>
Keywords: invideo-ai,mcp,claude,ai,video
Classifier: Development Status :: 3 - Alpha
Classifier: Intended Audience :: Developers
Classifier: Programming Language :: Python :: 3
Classifier: Programming Language :: Python :: 3.13
Requires-Python: >=3.13
Requires-Dist: anthropic>=0.49.0
Requires-Dist: httpx>=0.28.1
Requires-Dist: mcp[cli]>=1.6.0
Requires-Dist: pydantic>=2.11.3
Requires-Dist: python-dotenv>=1.1.0
